setup.cfg
setup.py
PyPI_TravisCI_Example/__init__.py
PyPI_TravisCI_Example/calculate.py
PyPI_TravisCI_Example.egg-info/PKG-INFO
PyPI_TravisCI_Example.egg-info/SOURCES.txt
PyPI_TravisCI_Example.egg-info/dependency_links.txt
PyPI_TravisCI_Example.egg-info/top_level.txt