Metadata-Version: 1.1
Name: PyPI-TravisCI-Example
Version: 0.1
Summary: An example for how to build project onto PyPI & TravisCI
Home-page: https://github.com/aweimeow/PyPI_TravisCI_Example
Author: aweimeow(Wei-You Chen)
Author-email: aweimemow.tw@gmail.com
License: UNKNOWN
Download-URL: https://github.com/aweimeow/PyPI_TravisCI_Example/archive/master.zip
Keywords: PyPI,TravisCI,example
Platform: UNKNOWN
